rundeck_exporter/__init__.py
rundeck_exporter/args.py
rundeck_exporter/cli.py
rundeck_exporter/constants.py
rundeck_exporter/metrics_collector.py
rundeck_exporter/utils.py
rundeck_exporter-3.0.3.dist-info/METADATA
rundeck_exporter-3.0.3.dist-info/WHEEL
rundeck_exporter-3.0.3.dist-info/entry_points.txt
rundeck_exporter-3.0.3.dist-info/RECORD
