Metadata-Version: 2.4
Name: rundeck_exporter
Version: 3.0.3
Summary: Rundeck metrics exporter for Prometheus
Project-URL: Repository, https://github.com/phsmith/rundeck_exporter
Project-URL: Issues, https://github.com/phsmith/rundeck_exporter/issues
Author-email: Phillipe Smith <phsmithcc@gmail.com>
Classifier: Development Status :: 5 - Production/Stable
Classifier: Environment :: Console
Classifier: Intended Audience :: Developers
Classifier: Intended Audience :: System Administrators
Classifier: Operating System :: OS Independent
Classifier: Programming Language :: Python
Classifier: Programming Language :: Python :: 3
Classifier: Programming Language :: Python :: 3.11
Classifier: Programming Language :: Python :: 3.12
Classifier: Programming Language :: Python :: 3.13
Requires-Python: <4.0,>=3.11
Requires-Dist: cachetools==5.5.0
Requires-Dist: prometheus-client==0.21.1
Requires-Dist: requests==2.32.4
